LICENSE
MANIFEST.in
README.md
setup.py
firehawk/__init__.py
firehawk/ddl.py
firehawk/graph.py
firehawk.egg-info/PKG-INFO
firehawk.egg-info/SOURCES.txt
firehawk.egg-info/dependency_links.txt
firehawk.egg-info/entry_points.txt
firehawk.egg-info/requires.txt
firehawk.egg-info/top_level.txt