Metadata-Version: 1.0
Name: firehawk
Version: 0.3
Summary: Alternative graph parsing language and REPL for DataStax Enterprise (DSE)
Home-page: https://github.com/rustyrazorblade/firehawk
Author: Jon Haddad
Author-email: jon@jonhaddad.com
License: License :: OSI Approved :: Apache Software License
Platform: UNKNOWN
